IceDtlsConnection/IceDtlsSocket.py
icedtlsconnection-0.9.0.dist-info/LICENSE
icedtlsconnection-0.9.0.dist-info/METADATA
icedtlsconnection-0.9.0.dist-info/WHEEL
icedtlsconnection-0.9.0.dist-info/top_level.txt
icedtlsconnection-0.9.0.dist-info/RECORD
